majors/__init__.py
majors/bond/__init__.py
majors/bond/bonds.py
majors/coins/__init__.py
majors/coins/market.py
majors/data/__init__.py
majors/fund/__init__.py
majors/fund/cons.py
majors/fund/nav.py
majors/futures/__init__.py
majors/futures/cons.py
majors/futures/domestic.py
majors/futures/domestic_cons.py
majors/futures/intlfutures.py
majors/internet/__init__.py
majors/internet/boxoffice.py
majors/internet/caixinnews.py
majors/internet/indexes.py
majors/pro/__init__.py
majors/pro/client.py
majors/pro/data_pro.py
majors/stock/__init__.py
majors/stock/billboard.py
majors/stock/classifying.py
majors/stock/cons.py
majors/stock/fundamental.py
majors/stock/globals.py
majors/stock/indictor.py
majors/stock/macro.py
majors/stock/macro_vars.py
majors/stock/minsdata.py
majors/stock/news_vars.py
majors/stock/newsevent.py
majors/stock/ref_vars.py
majors/stock/reference.py
majors/stock/shibor.py
majors/stock/trading.py
majors/subs/__init__.py
majors/subs/ts_subs.py
majors/subs/ht_subs/__init__.py
majors/subs/ht_subs/service/__init__.py
majors/subs/ht_subs/service/covert.py
majors/subs/model/__init__.py
majors/subs/model/min.py
majors/subs/model/tick.py
majors/trader/__init__.py
majors/trader/trader.py
majors/trader/utils.py
majors/trader/vars.py
majors/util/__init__.py
majors/util/common.py
majors/util/conns.py
majors/util/dateu.py
majors/util/formula.py
majors/util/mailmerge.py
majors/util/netbase.py
majors/util/store.py
majors/util/upass.py
majors/util/vars.py
majors/util/protobuf/__init__.py
majors/util/protobuf/funcs.py
majors/util/protobuf/response_pb2.py
majorsdata-0.0.1.dist-info/LICENSE
majorsdata-0.0.1.dist-info/METADATA
majorsdata-0.0.1.dist-info/WHEEL
majorsdata-0.0.1.dist-info/top_level.txt
majorsdata-0.0.1.dist-info/RECORD
